{
    "get": {
        "summary": "GetSignedContractDataByEmaidAndPcid",
        "operationId": "getSignedContractDataByEmaidAndPcidV1",
        "description": "The CCP offers this additional interface to provide signed contract data to OEM backends without the need of a CertificateInstallationRequest. The OEM backend requests the endpoint with an EMAID and a PCID to receive the certificateInstallationResponse.\n\nThe OEM backend must check the validity of the contract, before the installation into the car, whether it is expired or revoked.\n\n| Check                                            | \n|--------------------------------------------------|\n| Contract for EMAID must be existing in the pool. |",
        "tags": [
            "GetSignedContractDataByEmaidAndPcid"
        ],
        "parameters": [
            {
                "$ref": "../../components/parameters/headers/opncCorrelationId.v1.json"
            },
            {
                "$ref": "../../components/parameters/headers/opncRequestId.v1.json"
            },
            {
                "$ref": "../../components/parameters/headers/opncFromPartyType.v1.json"
            },
            {
                "$ref": "../../components/parameters/headers/opncFromPartyId.v1.json"
            },
            {
                "$ref": "../../components/parameters/headers/opncToPartyType.v1.json"
            },
            {
                "$ref": "../../components/parameters/headers/opncToPartyId.v1.json"
            },
            {
                "schema": {
                    "$ref": "../../components/parameters/emaidParam.v1.json"
                },
                "name": "emaid",
                "in": "path",
                "required": true,
                "description": "The EMAID of the requested contract."
            },
            {
                "name": "pcid",
                "in": "path",
                "required": true,
                "description": "The related provisioning certificate ID.",
                "schema": {
                    "$ref": "../../components/parameters/pcidParam.v1.json"
                }
            },
            {
                "schema": {
                    "type": "string",
                    "example": "00"
                },
                "in": "query",
                "name": "sessionID",
                "description": "Session ID as HEX shall be included into the xml if present",
                "allowEmptyValue": true
            },
            {
                "schema": {
                    "type": "string",
                    "default": "urn:iso:15118:2:2013:MsgDef",
                    "example": "urn:iso:15118:2:2013:MsgDef"
                },
                "in": "query",
                "name": "xsdMsgDefNamespace",
                "description": "To receive signed contract data for a specific ISO Version"
            },
            {
                "schema": {
                    "$ref": "../../components/parameters/cpsV2GRootCertificateFingerprintParam.v1.json"
                },
                "in": "query",
                "name": "cpsV2GRootCertificateFingerprint",
                "description": "The SHA256 Fingerprint of the desired V2G root CA which shall was used to sign these data with the regarding CPS signing certificate. Its optional. If not given, the CPS will decide which CPS signing V2G PKI will be renurned"
            }
        ],
        "responses": {
            "200": {
                "description": "OK",
                "headers": {
                    "OPNC-Correlation-ID": {
                        "$ref": "../../components/parameters/headers/opncCorrelationId.v1.json"
                    },
                    "OPNC-Request-ID": {
                        "$ref": "../../components/parameters/headers/opncRequestId.v1.json"
                    }
                },
                "content": {
                    "application/json": {
                        "schema": {
                            "$ref": "../../components/responses/getSignedContractDataRes.v1.json"
                        }
                    }
                }
            },
            "400": {
                "description": "Bad Request",
                "headers": {
                    "OPNC-Correlation-ID": {
                        "$ref": "../../components/parameters/headers/opncCorrelationId.v1.json"
                    },
                    "OPNC-Request-ID": {
                        "$ref": "../../components/parameters/headers/opncRequestId.v1.json"
                    }
                },
                "content": {
                    "application/json": {
                        "schema": {
                            "$ref": "../../components/schemas/error.v1.json"
                        },
                        "examples": {
                            "Invalid PCID": {
                                "value": {
                                    "errorMessages": [
                                        "pcid : must match \"^[a-zA-Z0-9]{17,18}$\""
                                    ],
                                    "traceId": "1c8c56cb-b71f-46a5-8788-5ddcedc88e2a"
                                }
                            },
                            "Invalid EMAID": {
                                "value": {
                                    "errorMessages": [
                                        "emaid : must match \"^[A-Za-z]{2}[-]?\\w{3}[-]?\\w{9,28}[-]?(\\w{1})?$\""
                                    ],
                                    "traceId": "02be5c05-298b-4503-a685-8126951e0233"
                                }
                            },
                            "Invalid SessionID": {
                                "value": {
                                    "errorMessages": [
                                        "Invalid SessionID format, make sure the length is maximum 8 characters and it is represented in HEX binary"
                                    ],
                                    "traceId": "5712b40b-5003-4553-8539-2d1edaf56b6a"
                                }
                            }
                        }
                    }
                }
            },
            "401": {
                "$ref": "../../components/responses/errorResponses/Unauthorized.json"
            },
            "403": {
                "$ref": "../../components/responses/errorResponses/Forbidden.json"
            },
            "404": {
                "$ref": "../../components/responses/errorResponses/NotFound.json"
            },
            "500": {
                "$ref": "../../components/responses/errorResponses/InternalServerError.json"
            },
            "502": {
                "$ref": "../../components/responses/errorResponses/BadGataway.json"
            },
            "503": {
                "$ref": "../../components/responses/errorResponses/ServiceUnavailable.json"
            }
        },
        "security": [
            {
                "OEM": []
            }
        ]
    }
}